CHANGELOG.txt
LICENSE.txt
MANIFEST.in
README.txt
setup.py
oripy/__init__.py
oripy/ai.py
oripy/tempCodeRunnerFile.py
oripy/text.py
oripy.egg-info/PKG-INFO
oripy.egg-info/SOURCES.txt
oripy.egg-info/dependency_links.txt
oripy.egg-info/requires.txt
oripy.egg-info/top_level.txt