Metadata-Version: 2.1
Name: oripy
Version: 3.0.0
Summary: Orisyne is a powerful and flexible computation package designed to streamline complex operations in data processing. With an intuitive interface and robust performance, Orisyne enables developers to efficiently handle intricate calculations, making it an essential tool for advanced data manipulation and analysis.
Home-page: 
Author: Bluemon Cybersec
Author-email: bluemoncybersec@gmail.com
License: MIT
Keywords: oripy
Classifier: Development Status :: 5 - Production/Stable
Classifier: Intended Audience :: Education
Classifier: Operating System :: Microsoft :: Windows :: Windows 10
Classifier: License :: OSI Approved :: MIT License
Classifier: Programming Language :: Python :: 3
License-File: LICENSE.txt
